obswsc/__init__.py
obswsc/client.py
obswsc/data.py
obswsc/enums.py
obswsc/registry.py
obs_ws_client-0.1.0.dist-info/LICENSE
obs_ws_client-0.1.0.dist-info/METADATA
obs_ws_client-0.1.0.dist-info/WHEEL
obs_ws_client-0.1.0.dist-info/RECORD
