Metadata-Version: 2.1
Name: obs-ws-client
Version: 0.1.0
Summary: A websocket client for OBS Studio in Python.
License: MIT
Keywords: obs,obs-studio,websocket,asyncio,client
Author: Elorfiniel
Author-email: markgenthusiastic@gmail.com
Requires-Python: >=3.9,<4.0
Classifier: Intended Audience :: Developers
Classifier: License :: OSI Approved :: MIT License
Classifier: Operating System :: OS Independent
Classifier: Programming Language :: Python :: 3
Classifier: Programming Language :: Python :: 3.9
Classifier: Programming Language :: Python :: 3.10
Classifier: Programming Language :: Python :: 3.11
Classifier: Programming Language :: Python :: 3.12
Requires-Dist: websockets (>=14.0,<15.0)
Project-URL: gitee, https://gitee.com/elorfiniel/obs-ws-client-python
Project-URL: github, https://github.com/Elorfiniel/obs-ws-client-python
